photoifu/__init__.py
photoifu/photoref.py
photoifu/slice.py
photoifu/utils.py
photoifu-0.1.0.dist-info/LICENSE
photoifu-0.1.0.dist-info/METADATA
photoifu-0.1.0.dist-info/WHEEL
photoifu-0.1.0.dist-info/top_level.txt
photoifu-0.1.0.dist-info/RECORD
