Metadata-Version: 2.1
Name: photoifu
Version: 0.1.0
Summary: Project Photometric images inside IFU and play with that
Home-page: https://github.com/MickaelRigault/photoifu
Author: Mickael Rigault
Author-email: m.rigault@ipnl.in2p3.fr
License: Apache Software License
Keywords: astronomy,astrophysics
Classifier: Development Status :: 2 - Pre-Alpha
Classifier: Intended Audience :: Science/Research
Classifier: License :: OSI Approved :: Apache Software License
Classifier: Programming Language :: Python :: 3
Classifier: Topic :: Scientific/Engineering :: Astronomy
Classifier: Topic :: Scientific/Engineering :: Physics
Requires-Python: >=3.10
License-File: LICENSE
Requires-Dist: numpy
Requires-Dist: pandas
Requires-Dist: scipy
Requires-Dist: matplotlib
Requires-Dist: pixelproject
Requires-Dist: propobject
Provides-Extra: docs
Requires-Dist: nbsphinx ; extra == 'docs'
Provides-Extra: tests
Requires-Dist: pytest ; extra == 'tests'
Requires-Dist: coverage ; extra == 'tests'
